<?xml version="1.0" encoding="UTF-8"?>

<datasources xmlns="http://www.jboss.org/ironjacamar/schema"
	xmlns:xsd="http://docs.jboss.org/ironjacamar/schema/datasources_1_1.xsd">

	<datasource jndi-name="java:jboss/datasources/slz-core-ds"
		pool-name="slz-core" enabled="true" use-java-context="true">
		<connection-url>jdbc:mysql://127.0.0.1:3306/slz_core</connection-url>
		<driver>mysql-connector-java-5.1.26-bin.jar</driver>
		<driver-class>com.mysql.jdbc.Driver</driver-class>
		<pool>
			<min-pool-size>5</min-pool-size>
			<max-pool-size>20</max-pool-size>
			<prefill>true</prefill>
			<use-strict-min>false</use-strict-min>
			<flush-strategy>FailingConnectionOnly</flush-strategy>
		</pool>
		<security>
			<user-name>slz02</user-name>
			<password>slz02@123</password>
		</security>
	</datasource>

</datasources>